[
  {
    "제80회 라이브 클럽 데이": [
      "https://ticket.melon.com/performance/index.htm?prodId=213090"
    ],
    "카오스": [
      "https://www.instagram.com/p/DVsPKl8EsIx/"
    ],
    "더쿠": [
      "https://www.instagram.com/p/DVsPKl8EsIx/"
    ],
    "문영": [
      "https://www.instagram.com/p/DW6ShmskS1N/"
    ],
    "오방가르드 8주년 공연 시리즈": [
      "https://linktr.ee/OVGD8thSeries"
    ],
    "CXC Fest Vol.1": [
      "https://booking.naver.com/booking/12/bizes/1293964/items/7583472?tab=details"
    ],
    "OurR": [
      "https://www.instagram.com/p/DXJYEI2kzKt/"
    ],
    "non non": [
      "https://www.instagram.com/p/DW3b2sDDLAw/"
    ],
    "태평성대": [
      "https://www.instagram.com/p/DXJUOQWD8_d/"
    ]
  },
  {
    "showdeeId": 528977,
    "source": "showdee",
    "artists": [
      "CXC Fest Vol.1"
    ],
    "location": "세티라이브홀, 프리즘홀",
    "date": "2026-05-02",
    "startTime": "2026-05-02T16:00:00.000+09:00",
    "eventUrl": "https://booking.naver.com/booking/12/bizes/1293964/items/7583472?tab=details",
    "entry": "예매 링크",
    "imgSrc": null,
    "unmatchedReason": "unknown"
  },
  {
    "date": "2026-04-24T00:00:00.000",
    "startTime": "2026-04-24T21:00:00.000",
    "endTime": "2026-04-25T07:00:00.000",
    "eventUrl": "https://ra.co/events/2425644",
    "title": "𝐖𝐀𝐈𝐊𝐈𝐊𝐈 𝐔𝐓𝐎𝐏𝐈𝐀 '𝐉𝐔𝐍𝐆 𝐒𝐀𝐍𝐆𝐒𝐎𝐎'",
    "location": "Waikiki Utopia",
    "artists": [
      "TERRA (KR)",
      "NEO KR",
      "H93 (KR)",
      "AVEN (KR)",
      "STAN MYLOR",
      "HADO (KR)",
      "KWONNY",
      "SELL (KR)"
    ],
    "source": "ra",
    "ra_id": 288423
  },
  {
    "date": "2026-04-25T00:00:00.000",
    "startTime": "2026-04-25T21:00:00.000",
    "endTime": "2026-04-26T07:00:00.000",
    "eventUrl": "https://ra.co/events/2425649",
    "title": "𝐖𝐀𝐈𝐊𝐈𝐊𝐈 𝐔𝐓𝐎𝐏𝐈𝐀 '𝐔𝐓𝐎𝐏𝐈𝐀: 𝐆𝐋𝐎𝐁𝐀𝐋 𝐒𝐎𝐔𝐍𝐃'",
    "location": "Waikiki Utopia",
    "artists": [
      "TERRA (KR)",
      "NEO KR",
      "H93 (KR)",
      "AVEN (KR)",
      "STAN MYLOR",
      "HADO (KR)",
      "KWONNY",
      "SELL (KR)"
    ],
    "source": "ra",
    "ra_id": 288423
  },
  {
    "date": "2026-04-30T00:00:00.000",
    "startTime": "2026-04-30T20:00:00.000",
    "endTime": "2026-04-30T23:59:00.000",
    "eventUrl": "https://ra.co/events/2391382",
    "title": "MRZ DJ SET: ASIA TOUR",
    "location": "TBA",
    "artists": [
      "MRZ (1)"
    ],
    "source": "ra",
    "unmatchedReason": "TBA"
  },
  {
    "date": "2026-05-01T00:00:00.000",
    "startTime": "2026-05-01T21:00:00.000",
    "endTime": "2026-05-01T23:59:00.000",
    "eventUrl": "https://ra.co/events/2347177",
    "title": "MRZ DJ SET: MARQUE D'AMOUR SEOUL",
    "location": "TBA",
    "artists": [
      "MRZ (1)"
    ],
    "source": "ra",
    "unmatchedReason": "TBA"
  },
  {
    "date": "2026-05-01T00:00:00.000",
    "startTime": "2026-05-01T21:00:00.000",
    "endTime": "2026-05-02T23:00:00.000",
    "eventUrl": "https://ra.co/events/2347059",
    "title": "MRZ DJ: SOUTH KOREA TOUR",
    "location": "TBA",
    "artists": [
      "MRZ (1)"
    ],
    "source": "ra",
    "unmatchedReason": "TBA"
  },
  {
    "date": "2026-05-02T00:00:00.000",
    "startTime": "2026-05-02T16:30:00.000",
    "endTime": "2026-05-02T19:00:00.000",
    "eventUrl": "https://ra.co/events/2418133",
    "title": "live: Neuter, Han Gil Jang, Haku Sungho",
    "location": "Aapex",
    "artists": [],
    "source": "ra",
    "ra_id": 289942
  },
  {
    "date": "2026-05-02T00:00:00.000",
    "startTime": "2026-05-01T21:00:00.000",
    "endTime": "2026-05-02T23:00:00.000",
    "eventUrl": "https://ra.co/events/2347059",
    "title": "MRZ DJ: SOUTH KOREA TOUR",
    "location": "TBA",
    "artists": [
      "MRZ (1)"
    ],
    "source": "ra",
    "unmatchedReason": "TBA"
  },
  {
    "date": "2026-05-09T00:00:00.000",
    "startTime": "2026-05-09T20:00:00.000",
    "endTime": "2026-05-10T06:00:00.000",
    "eventUrl": "https://ra.co/events/2419032",
    "title": "FRISK Garden",
    "location": "TBA - FRISK Garden",
    "artists": [
      "Davico",
      "Demuk",
      "Sudowoo",
      "Departs",
      "Jaebin",
      "ploud"
    ],
    "source": "ra",
    "unmatchedReason": "TBA"
  },
  {
    "date": "2026-05-09T00:00:00.000",
    "startTime": "2026-05-09T17:00:00.000",
    "endTime": "2026-05-10T17:00:00.000",
    "eventUrl": "https://ra.co/events/2353858",
    "title": "Prompt 2026",
    "location": "TBA - 강원도 화천",
    "artists": [
      "ComaRobot",
      "Radio Revolution",
      "DJ Jinwook",
      "Haemi Park",
      "NON IDENTITY",
      "Hii.",
      "ccb",
      "Pyramid of Knowledge",
      "Pseudobaul",
      "Zoonpark",
      "Hogun",
      "OENN",
      "Jiyoo",
      "Shingo",
      "Simone Bauer",
      "S-Pill",
      "Teik Arô"
    ],
    "source": "ra",
    "unmatchedReason": "TBA"
  },
  {
    "date": "2026-05-10T00:00:00.000",
    "startTime": "2026-05-10T17:00:00.000",
    "endTime": "2026-05-10T19:00:00.000",
    "eventUrl": "https://ra.co/events/2425209",
    "title": "REPERCUSSION",
    "location": "Wumuji",
    "artists": [
      "Vahakn"
    ],
    "source": "ra",
    "ra_id": 290683
  },
  {
    "date": "2026-05-16T00:00:00.000",
    "startTime": "2026-05-16T22:00:00.000",
    "endTime": "2026-05-17T05:00:00.000",
    "eventUrl": "https://ra.co/events/2416640",
    "title": "Teum, Secret location. May 16",
    "location": "TBA - Secret location, Busan, Korea",
    "artists": [],
    "source": "ra",
    "unmatchedReason": "TBA"
  },
  {
    "date": "2026-05-25T00:00:00.000",
    "startTime": "2026-05-25T15:00:00.000",
    "endTime": "2026-05-25T21:00:00.000",
    "eventUrl": "https://ra.co/events/2422264",
    "title": "Sundrift x WHPH: Effervescent Flow",
    "location": "TBA",
    "artists": [
      "Coolrnch",
      "y3jin"
    ],
    "source": "ra",
    "unmatchedReason": "TBA"
  },
  {
    "date": "2026-06-05T00:00:00.000",
    "startTime": "2026-06-05T17:00:00.000",
    "endTime": "2026-06-07T09:00:00.000",
    "eventUrl": "https://ra.co/events/2382075",
    "title": "Hahoe Festival",
    "location": "TBA - Korean Culture Theme Park, Andong",
    "artists": [
      "Afrodite (2)",
      "Airbear",
      "Bolm",
      "chukimaandal",
      "Cozyhoon",
      "Closet Yi",
      "DIEGO (KR)",
      "E3",
      "Gumi",
      "Hogun",
      "Jimin",
      "DJ Jinwook",
      "Jiyoo",
      "JNS",
      "Joon Kwak",
      "Juncheol",
      "Kugel",
      "kimmtae",
      "Keemyo",
      "Kimmingi",
      "KYO (2)",
      "Maki",
      "mizae lim",
      "MUI (KR)",
      "NUSNOOM",
      "OENN",
      "Oldshoes",
      "Pseudobaul",
      "Radiofear",
      "Radio Revolution",
      "Short Finger",
      "SINAE",
      "Soyo",
      "Sun Gin",
      "TAERI KIM",
      "Taeri",
      "Ve Bogel",
      "Xanexx",
      "XXOK",
      "Zoonpark"
    ],
    "source": "ra",
    "unmatchedReason": "TBA"
  },
  {
    "date": "2026-06-06T00:00:00.000",
    "startTime": "2026-06-05T17:00:00.000",
    "endTime": "2026-06-07T09:00:00.000",
    "eventUrl": "https://ra.co/events/2382075",
    "title": "Hahoe Festival",
    "location": "TBA - Korean Culture Theme Park, Andong",
    "artists": [
      "Afrodite (2)",
      "Airbear",
      "Bolm",
      "chukimaandal",
      "Cozyhoon",
      "Closet Yi",
      "DIEGO (KR)",
      "E3",
      "Gumi",
      "Hogun",
      "Jimin",
      "DJ Jinwook",
      "Jiyoo",
      "JNS",
      "Joon Kwak",
      "Juncheol",
      "Kugel",
      "kimmtae",
      "Keemyo",
      "Kimmingi",
      "KYO (2)",
      "Maki",
      "mizae lim",
      "MUI (KR)",
      "NUSNOOM",
      "OENN",
      "Oldshoes",
      "Pseudobaul",
      "Radiofear",
      "Radio Revolution",
      "Short Finger",
      "SINAE",
      "Soyo",
      "Sun Gin",
      "TAERI KIM",
      "Taeri",
      "Ve Bogel",
      "Xanexx",
      "XXOK",
      "Zoonpark"
    ],
    "source": "ra",
    "unmatchedReason": "TBA"
  },
  {
    "date": "2026-06-12T00:00:00.000",
    "startTime": "2026-06-12T14:00:00.000",
    "endTime": "2026-06-14T12:00:00.000",
    "eventUrl": "https://ra.co/events/2410011",
    "title": "SYNTHASIA Open Air: Saldun",
    "location": "Saldun",
    "artists": [
      "Astma（JP）",
      "Carrier",
      "Chingyi",
      "comm",
      "Inn (TW)",
      "Inqapool",
      "Jama (2)",
      "KMG",
      "Koichi Shimizu",
      "Konnection",
      "KOSEI",
      "Krijka",
      "Kugel",
      "NAMASIS",
      "Perila",
      "Purusha",
      "R-010",
      "rye seon",
      "Scøpe",
      "Shao",
      "SIJIN",
      "Siot",
      "Marco Yanes",
      "Yuki Matsumura"
    ],
    "source": "ra",
    "ra_id": 289106
  },
  {
    "date": "2026-06-12T00:00:00.000",
    "startTime": "2026-06-12T19:00:00.000",
    "endTime": "2026-06-14T23:59:00.000",
    "eventUrl": "https://ra.co/events/2417817",
    "title": "DMZ Peace Train MUSIC FESTIVAL 2026",
    "location": "Goseokjeong, Cheorwon",
    "artists": [
      "Nourished by Time"
    ],
    "source": "ra",
    "ra_id": 215994
  },
  {
    "date": "2026-06-13T00:00:00.000",
    "startTime": "2026-06-12T14:00:00.000",
    "endTime": "2026-06-14T12:00:00.000",
    "eventUrl": "https://ra.co/events/2410011",
    "title": "SYNTHASIA Open Air: Saldun",
    "location": "Saldun",
    "artists": [
      "Astma（JP）",
      "Carrier",
      "Chingyi",
      "comm",
      "Inn (TW)",
      "Inqapool",
      "Jama (2)",
      "KMG",
      "Koichi Shimizu",
      "Konnection",
      "KOSEI",
      "Krijka",
      "Kugel",
      "NAMASIS",
      "Perila",
      "Purusha",
      "R-010",
      "rye seon",
      "Scøpe",
      "Shao",
      "SIJIN",
      "Siot",
      "Marco Yanes",
      "Yuki Matsumura"
    ],
    "source": "ra",
    "ra_id": 289106
  },
  {
    "date": "2026-06-13T00:00:00.000",
    "startTime": "2026-06-12T19:00:00.000",
    "endTime": "2026-06-14T23:59:00.000",
    "eventUrl": "https://ra.co/events/2417817",
    "title": "DMZ Peace Train MUSIC FESTIVAL 2026",
    "location": "Goseokjeong, Cheorwon",
    "artists": [
      "Nourished by Time"
    ],
    "source": "ra",
    "ra_id": 215994
  },
  {
    "date": "2026-06-14T00:00:00.000",
    "startTime": "2026-06-12T19:00:00.000",
    "endTime": "2026-06-14T23:59:00.000",
    "eventUrl": "https://ra.co/events/2417817",
    "title": "DMZ Peace Train MUSIC FESTIVAL 2026",
    "location": "Goseokjeong, Cheorwon",
    "artists": [
      "Nourished by Time"
    ],
    "source": "ra",
    "ra_id": 215994
  }
]